tgw_route_manager/__init__.py
tgw_route_manager/index.py
tgw_route_manager-1.2.dist-info/METADATA
tgw_route_manager-1.2.dist-info/WHEEL
tgw_route_manager-1.2.dist-info/top_level.txt
tgw_route_manager-1.2.dist-info/RECORD
