Metadata-Version: 2.1
Name: tgw-route-manager
Version: 1.2
Summary: Manage AWS Transit Gateway route with Cloudformation
Home-page: http://github.com/droidlabour
Author: Joy Prakash Sharma
Author-email: droidlabour@gmail.com
License: MIT
Platform: UNKNOWN
Classifier: Development Status :: 3 - Alpha
Classifier: License :: OSI Approved :: MIT License
Classifier: Programming Language :: Python :: 3.7
Requires-Dist: boto3 (==1.9.130)
Requires-Dist: cfnresponse
